[
    {
        "TopicNum": 0,
        "keywords": [
            "prices",
            "rose",
            "earnings",
            "index",
            "fell",
            "sales",
            "stocks",
            "vastpress vastopolis",
            "million cents",
            "thousand shares",
            "reals thousand",
            "million shares",
            "cents share",
            "capital gains",
            "stock exchange"
        ]
    },
    {
        "TopicNum": 1,
        "keywords": [
            "business",
            "saudi",
            "years ago",
            "lloyd",
            "bomb",
            "codi",
            "atlanta",
            "security",
            "party",
            "president",
            "funds",
            "mr derryberry",
            "vastpress vastopolis",
            "hong kong",
            "games"
        ]
    },
    {
        "TopicNum": 2,
        "keywords": [
            "shares",
            "stock exchange",
            "industry",
            "line",
            "fidelity",
            "assets",
            "jardine fleming",
            "hong kong",
            "insurance",
            "securities",
            "vastpress vastopolis",
            "management",
            "business",
            "lloyd",
            "funds"
        ]
    },
    {
        "TopicNum": 3,
        "keywords": [
            "prices",
            "rose",
            "earnings",
            "index",
            "fell",
            "sales",
            "stocks",
            "vastpress vastopolis",
            "million cents",
            "thousand shares",
            "reals thousand",
            "million shares",
            "cents share",
            "capital gains",
            "stock exchange"
        ]
    },
    {
        "TopicNum": 4,
        "keywords": [
            "airport",
            "flight",
            "years ago",
            "mr codi",
            "bombing",
            "saudi arabia",
            "airlines",
            "vastpress vastopolis",
            "atlanta",
            "security",
            "party",
            "president",
            "hong kong",
            "mr derryberry",
            "games"
        ]
    },
    {
        "TopicNum": 5,
        "keywords": [
            "securities",
            "million cents",
            "thousand shares",
            "reals thousand",
            "million shares",
            "cents share",
            "capital gains",
            "stock exchange",
            "management",
            "mr",
            "business",
            "hong kong",
            "lloyd",
            "vastpress vastopolis",
            "funds"
        ]
    },
    {
        "TopicNum": 6,
        "keywords": [
            "prices",
            "rose",
            "earnings",
            "index",
            "fell",
            "sales",
            "stocks",
            "vastpress vastopolis",
            "million cents",
            "thousand shares",
            "reals thousand",
            "million shares",
            "cents share",
            "capital gains",
            "stock exchange"
        ]
    },
    {
        "TopicNum": 7,
        "keywords": [
            "games",
            "fell",
            "sales",
            "stocks",
            "funds",
            "mr",
            "hong kong",
            "million cents",
            "thousand shares",
            "reals thousand",
            "million shares",
            "cents share",
            "capital gains",
            "stock exchange",
            "vastpress vastopolis"
        ]
    },
    {
        "TopicNum": 8,
        "keywords": [
            "london",
            "money",
            "mutual funds",
            "coca cola",
            "hong kong",
            "industry",
            "line",
            "fidelity",
            "assets",
            "jardine fleming",
            "insurance",
            "securities",
            "management",
            "business",
            "lloyd"
        ]
    }
]