[
 {
  "keywords": [
   "share", 
   "market", 
   "stock", 
   "compani", 
   "million", 
   "price", 
   "cent", 
   "year", 
   "fell", 
   "index", 
   "trade", 
   "billion", 
   "sale", 
   "rose", 
   "investor"
  ], 
  "TopicNum: ": 0
 }, 
 {
  "keywords": [
   "year", 
   "fund", 
   "presid", 
   "bond", 
   "bankruptci", 
   "bank", 
   "pain", 
   "manag", 
   ".''", 
   "credit", 
   "market", 
   "peopl", 
   "taiwan", 
   "debt", 
   "new"
  ], 
  "TopicNum: ": 1
 }, 
 {
  "keywords": [
   "tax", 
   "bomb", 
   "new", 
   "airlin", 
   "rate", 
   "secur", 
   "airport", 
   "capit", 
   ".''", 
   "year", 
   "lloyd", 
   "game", 
   "terrorist", 
   "gain", 
   "compani"
  ], 
  "TopicNum: ": 2
 }, 
 {
  "keywords": [
   "year", 
   "compani", 
   "parti", 
   "player", 
   "million", 
   "team", 
   "new", 
   ".''", 
   "may", 
   "racket", 
   "shubert", 
   "japan", 
   "presid", 
   "last", 
   "polic"
  ], 
  "TopicNum: ": 3
 }, 
 {
  "keywords": [
   "plant", 
   "game", 
   "union", 
   "atlanta", 
   ".''", 
   "citi", 
   "year", 
   "liquid", 
   "threat", 
   "make", 
   "rule", 
   "may", 
   "gun", 
   "contract", 
   "luxembourg"
  ], 
  "TopicNum: ": 4
 }, 
 {
  "keywords": [
   "fund", 
   "manag", 
   "fidel", 
   "compani", 
   "bomb", 
   "secur", 
   "invest", 
   "mutual", 
   "group", 
   "also", 
   "fleme", 
   "asset", 
   ".''", 
   "saudi", 
   "offici"
  ], 
  "TopicNum: ": 5
 }, 
 {
  "keywords": [
   "year", 
   ".''", 
   "derryberri", 
   "game", 
   "new", 
   "world", 
   "countri", 
   "farmer", 
   "case", 
   "tractor", 
   "electr", 
   "presid", 
   "plan", 
   "charact", 
   "day"
  ], 
  "TopicNum: ": 6
 }, 
 {
  "keywords": [
   "book", 
   "presid", 
   "missil", 
   "year", 
   "pill", 
   "codi", 
   "issu", 
   "democrat", 
   ".''", 
   "china", 
   "time", 
   "women", 
   "may", 
   "derryberri", 
   "health"
  ], 
  "TopicNum: ": 7
 }
]