[
 {
  "keywords": [
   "hous", 
   "bukhari", 
   "polic", 
   "ammunit", 
   "date", 
   "gun", 
   "militari", 
   "octob", 
   "investig", 
   "kenya", 
   "sudan", 
   "believ", 
   "oper", 
   "town", 
   "box"
  ], 
  "TopicNum: ": 0
 }, 
 {
  "keywords": [
   "arm", 
   "minski", 
   "polic", 
   "found", 
   "intern", 
   "italian", 
   "date", 
   "deal", 
   "offic", 
   "yemen", 
   "room", 
   "court", 
   "diamond", 
   "forc", 
   "investig"
  ], 
  "TopicNum: ": 1
 }, 
 {
  "keywords": [
   "meet", 
   "call", 
   "place", 
   "phone", 
   "intercept", 
   "decemb", 
   "mobil", 
   "khouri", 
   "regist", 
   "arrang", 
   "contract", 
   "telephon", 
   "travel", 
   "april", 
   "tye"
  ], 
  "TopicNum: ": 2
 }, 
 {
  "keywords": [
   "caller", 
   "arm", 
   "kasem", 
   "call", 
   "phone", 
   "intercept", 
   "gun", 
   "place", 
   "receiv", 
   "part", 
   "telephon", 
   "anka", 
   "cell", 
   "ahm", 
   "apart"
  ], 
  "TopicNum: ": 3
 }, 
 {
  "keywords": [
   "weapon", 
   "basra", 
   "contract", 
   "bangkok", 
   "north", 
   "plane", 
   "inform", 
   "tanya", 
   "provid", 
   "korea", 
   "karachi", 
   "bukhari", 
   "left", 
   "arm", 
   "head"
  ], 
  "TopicNum: ": 4
 }, 
 {
  "keywords": [
   "bhutani", 
   "inform", 
   "yemen", 
   "men", 
   "bukhari", 
   "provid", 
   "may", 
   "date", 
   "death", 
   "follow", 
   "left", 
   "karachi", 
   "trade", 
   "flight", 
   "build"
  ], 
  "TopicNum: ": 5
 }, 
 {
  "keywords": [
   "fund", 
   "contract", 
   "intercept", 
   "bank", 
   "transfer", 
   "date", 
   "nigeria", 
   "part", 
   "transact", 
   "make", 
   "amount", 
   "inform", 
   "take", 
   "share", 
   "success"
  ], 
  "TopicNum: ": 6
 }, 
 {
  "keywords": [
   "pakistani", 
   "april", 
   "nation", 
   "apart", 
   "hard", 
   "jhangvi", 
   "ident", 
   "card", 
   "tlhe", 
   "januari", 
   "ali", 
   "lahor", 
   "name", 
   "found", 
   "provid"
  ], 
  "TopicNum: ": 7
 }
]