[
 {
  "keywords": [
   "arm", 
   "saudi", 
   "part", 
   "weapon", 
   "yemen", 
   "firearm", 
   "gun", 
   "receiv", 
   "date", 
   "court", 
   "call", 
   "year", 
   "yemeni", 
   "north", 
   "illeg"
  ], 
  "TopicNum: ": 0
 }, 
 {
  "keywords": [
   "sudan", 
   "contract", 
   "fund", 
   "transfer", 
   "arm", 
   "date", 
   "speaker", 
   "bank", 
   "transact", 
   "project", 
   "nigeria", 
   "kenya", 
   "intercept", 
   "gun", 
   "tanya"
  ], 
  "TopicNum: ": 1
 }, 
 {
  "keywords": [
   "gun", 
   "contract", 
   "arm", 
   "busi", 
   "bangkok", 
   "plane", 
   "inform", 
   "year", 
   "mikhail", 
   "weapon", 
   "health", 
   "thai", 
   "stand", 
   "compani", 
   "abl"
  ], 
  "TopicNum: ": 2
 }, 
 {
  "keywords": [
   "arm", 
   "polic", 
   "secur", 
   "oper", 
   "forc", 
   "offic", 
   "gun", 
   "also", 
   "april", 
   "date", 
   "kenya", 
   "arrest", 
   "ammunit", 
   "investig", 
   "question"
  ], 
  "TopicNum: ": 3
 }, 
 {
  "keywords": [
   "minski", 
   "kasem", 
   "arm", 
   "found", 
   "polic", 
   "italian", 
   "gun", 
   "intern", 
   "anka", 
   "room", 
   "money", 
   "diamond", 
   "involv", 
   "yemen", 
   "hotel"
  ], 
  "TopicNum: ": 4
 }, 
 {
  "keywords": [
   "caller", 
   "call", 
   "phone", 
   "place", 
   "money", 
   "intercept", 
   "bukhari", 
   "meet", 
   "telephon", 
   "inform", 
   "karachi", 
   "mobil", 
   "decemb", 
   "arrang", 
   "make"
  ], 
  "TopicNum: ": 5
 }, 
 {
  "keywords": [
   "part", 
   "octob", 
   "jtomski", 
   "intercept", 
   "board", 
   "bhutani", 
   "offic", 
   "mani", 
   "train", 
   "report", 
   "meet", 
   "date", 
   "inform", 
   "command", 
   "septemb"
  ], 
  "TopicNum: ": 6
 }
]