[
    {
        "TopicNum": 0,
        "keywords": [
            "family",
            "abila kronos",
            "protests",
            "minister",
            "gastech",
            "death",
            "protectors kronos",
            "contamination",
            "wfa",
            "pok",
            "water",
            "police force",
            "elian karel",
            "health",
            "elodis"
        ]
    },
    {
        "TopicNum": 1,
        "keywords": [
            "police",
            "approximately",
            "conference",
            "arrived",
            "construction",
            "abila kronos",
            "gastech employees",
            "emergency gastech",
            "gastech headquarters",
            "maha salo",
            "january modernization",
            "important people",
            "homeland illumination",
            "scene blog",
            "voices blog"
        ]
    },
    {
        "TopicNum": 2,
        "keywords": [
            "abila kronos",
            "gastech employees",
            "fire",
            "environmental",
            "place",
            "recent",
            "tethys",
            "local",
            "meeting",
            "tiskele",
            "ceo sten",
            "gastech international",
            "gastech kronos",
            "sten sanjorge",
            "sanjorge jr"
        ]
    },
    {
        "TopicNum": 3,
        "keywords": [
            "place",
            "recent",
            "local",
            "abila kronos",
            "tethys",
            "police force",
            "health",
            "meeting",
            "tiskele",
            "ceo sten",
            "gastech international",
            "elodis",
            "gastech kronos",
            "sten sanjorge",
            "sanjorge jr"
        ]
    },
    {
        "TopicNum": 4,
        "keywords": [
            "protests",
            "minister",
            "sanjorge jr",
            "death",
            "contamination",
            "protectors kronos",
            "wfa",
            "abila kronos",
            "pok",
            "water",
            "police force",
            "elian karel",
            "gastech",
            "health",
            "elodis"
        ]
    },
    {
        "TopicNum": 5,
        "keywords": [
            "arrived",
            "construction",
            "gastech kronos",
            "sten sanjorge",
            "sanjorge jr",
            "abila kronos",
            "gastech employees",
            "emergency gastech",
            "gastech headquarters",
            "maha salo",
            "january modernization",
            "important people",
            "homeland illumination",
            "scene blog",
            "voices blog"
        ]
    },
    {
        "TopicNum": 6,
        "keywords": [
            "police",
            "approximately",
            "conference",
            "arrived",
            "construction",
            "abila kronos",
            "gastech employees",
            "emergency gastech",
            "gastech headquarters",
            "maha salo",
            "january modernization",
            "important people",
            "homeland illumination",
            "scene blog",
            "voices blog"
        ]
    },
    {
        "TopicNum": 7,
        "keywords": [
            "construction",
            "elian karel",
            "health",
            "police force",
            "gastech employees",
            "elodis",
            "abila kronos",
            "emergency gastech",
            "gastech headquarters",
            "maha salo",
            "january modernization",
            "important people",
            "homeland illumination",
            "scene blog",
            "voices blog"
        ]
    }
]