[
    {
        "TopicNum": 0,
        "keywords": [
            "securities",
            "chairman",
            "million",
            "jardine fleming",
            "lloyd",
            "quarter",
            "prices",
            "earnings",
            "vastpress vastopolis",
            "mr",
            "funds",
            "sales",
            "billion",
            "company",
            "vice president"
        ]
    },
    {
        "TopicNum": 1,
        "keywords": [
            "atlanta",
            "airlines",
            "million cents",
            "bankruptcy",
            "years ago",
            "stock exchange",
            "bombing",
            "thousand shares",
            "reals thousand",
            "million shares",
            "mr derryberry",
            "games",
            "hong kong",
            "cents hk",
            "vastpress vastopolis"
        ]
    },
    {
        "TopicNum": 2,
        "keywords": [
            "sales",
            "traders",
            "points",
            "volume",
            "fell",
            "index",
            "vastpress vastopolis",
            "million cents",
            "cents share",
            "stock exchange",
            "hong kong",
            "thousand shares",
            "reals thousand",
            "million shares",
            "cents hk"
        ]
    },
    {
        "TopicNum": 3,
        "keywords": [
            "million cents",
            "lloyd",
            "jardine fleming",
            "cents hk",
            "cents share",
            "bomb",
            "years ago",
            "mr derryberry",
            "games",
            "funds",
            "hong kong",
            "billion",
            "company",
            "vice president",
            "vastpress vastopolis"
        ]
    },
    {
        "TopicNum": 4,
        "keywords": [
            "company",
            "quarter",
            "vice president",
            "prices",
            "earnings",
            "sales",
            "million cents",
            "stock exchange",
            "hong kong",
            "thousand shares",
            "reals thousand",
            "million shares",
            "cents share",
            "vastpress vastopolis",
            "cents hk"
        ]
    },
    {
        "TopicNum": 5,
        "keywords": [
            "prices",
            "volume",
            "earnings",
            "fell",
            "index",
            "sales",
            "million cents",
            "vastpress vastopolis",
            "cents share",
            "stock exchange",
            "hong kong",
            "thousand shares",
            "reals thousand",
            "million shares",
            "cents hk"
        ]
    }
]